dataprecf/__init__.py
dataprecf/categorical_encoder.py
dataprecf/data_type_converter.py
dataprecf/datetime_handler.py
dataprecf/feature_engineer.py
dataprecf/missing_value_handler.py
dataprecf/outlier_handler.py
dataprecf/scaler.py
dataprecf/text_cleaner.py
dataprecf-0.11.0.dist-info/METADATA
dataprecf-0.11.0.dist-info/WHEEL
dataprecf-0.11.0.dist-info/top_level.txt
dataprecf-0.11.0.dist-info/RECORD
