Metadata-Version: 2.1
Name: dataprecf
Version: 0.11.0
Summary: A data preprocessor for machine learning projects.
Author: fatmanur caliskan, cihan yilmaz
Author-email: fatmanur.caliskan@stu.fsm.edu.tr, cihan.yilmaz@stu.fsm.edu.tr
Classifier: Programming Language :: Python :: 3
Classifier: License :: OSI Approved :: MIT License
Classifier: Operating System :: OS Independent
Requires-Python: >=3.6
Requires-Dist: pandas
Requires-Dist: numpy
Requires-Dist: scikit-learn
Requires-Dist: nltk
